btsc/__init__.py
btsc/app.py
btsc-0.0.3.dist-info/LICENSE
btsc-0.0.3.dist-info/METADATA
btsc-0.0.3.dist-info/WHEEL
btsc-0.0.3.dist-info/entry_points.txt
btsc-0.0.3.dist-info/top_level.txt
btsc-0.0.3.dist-info/RECORD
