Metadata-Version: 2.1
Name: btsc
Version: 0.0.3
Summary: transfer.sh client
Home-page: https://github.com/preposing/btsc.git
Author: preposing
Author-email: sebdevpy@gmail.com
License: MIT
Keywords: transfer.sh client tool utility cli CLI
Classifier: Development Status :: 3 - Alpha
Classifier: Intended Audience :: Developers
Classifier: Topic :: Utilities
Classifier: Environment :: Console
Classifier: License :: OSI Approved :: MIT License
Classifier: Programming Language :: Python :: 3.5
License-File: LICENSE
